{
  "id": "3468084",
  "name": "cms2.0",
  "font_family": "iconfont",
  "css_prefix_text": "icon-",
  "description": "",
  "glyphs": [
    {
      "icon_id": "1246667",
      "name": "微信支付",
      "font_class": "weixinzhifu",
      "unicode": "e653",
      "unicode_decimal": 58963
    },
    {
      "icon_id": "7373152",
      "name": "搜索",
      "font_class": "sousuo",
      "unicode": "e60e",
      "unicode_decimal": 58894
    },
    {
      "icon_id": "8190454",
      "name": "视频",
      "font_class": "shipin_Linear",
      "unicode": "e676",
      "unicode_decimal": 58998
    },
    {
      "icon_id": "9874480",
      "name": "KHCFDC_返回",
      "font_class": "fanhui1",
      "unicode": "e6cc",
      "unicode_decimal": 59084
    },
    {
      "icon_id": "10299091",
      "name": "配送中",
      "font_class": "peisongzhong",
      "unicode": "e600",
      "unicode_decimal": 58880
    },
    {
      "icon_id": "10299099",
      "name": "待配送",
      "font_class": "daipeisong",
      "unicode": "e601",
      "unicode_decimal": 58881
    },
    {
      "icon_id": "13543861",
      "name": "扫码",
      "font_class": "saoma",
      "unicode": "e626",
      "unicode_decimal": 58918
    },
    {
      "icon_id": "1309508",
      "name": "权限",
      "font_class": "quanxian",
      "unicode": "e612",
      "unicode_decimal": 58898
    },
    {
      "icon_id": "2468136",
      "name": "权限管理",
      "font_class": "quanxianguanli",
      "unicode": "e617",
      "unicode_decimal": 58903
    },
    {
      "icon_id": "3266595",
      "name": "经理",
      "font_class": "jingli",
      "unicode": "e602",
      "unicode_decimal": 58882
    },
    {
      "icon_id": "4305650",
      "name": "我的学生",
      "font_class": "wodexuesheng",
      "unicode": "e67d",
      "unicode_decimal": 59005
    },
    {
      "icon_id": "4867090",
      "name": "设置",
      "font_class": "shezhi",
      "unicode": "e655",
      "unicode_decimal": 58965
    },
    {
      "icon_id": "5078869",
      "name": "角色授权",
      "font_class": "jiaoseshouquan",
      "unicode": "e642",
      "unicode_decimal": 58946
    },
    {
      "icon_id": "5081213",
      "name": "用户角色维护",
      "font_class": "yonghujiaoseweihu",
      "unicode": "e645",
      "unicode_decimal": 58949
    },
    {
      "icon_id": "5953439",
      "name": "功能",
      "font_class": "gongneng",
      "unicode": "e68c",
      "unicode_decimal": 59020
    },
    {
      "icon_id": "6989733",
      "name": "模块",
      "font_class": "mokuai1",
      "unicode": "e604",
      "unicode_decimal": 58884
    },
    {
      "icon_id": "7942731",
      "name": "功能开发",
      "font_class": "gongnengkaifa",
      "unicode": "e610",
      "unicode_decimal": 58896
    },
    {
      "icon_id": "8092004",
      "name": "模块",
      "font_class": "mokuai",
      "unicode": "e643",
      "unicode_decimal": 58947
    },
    {
      "icon_id": "10017665",
      "name": "模块管理",
      "font_class": "mokuaiguanli",
      "unicode": "e619",
      "unicode_decimal": 58905
    },
    {
      "icon_id": "10111306",
      "name": "设置",
      "font_class": "shezhi1",
      "unicode": "e61a",
      "unicode_decimal": 58906
    },
    {
      "icon_id": "10126624",
      "name": "功能反馈",
      "font_class": "gongnengfankui",
      "unicode": "e6a2",
      "unicode_decimal": 59042
    },
    {
      "icon_id": "10792640",
      "name": "新增角色用户_新增新建操作_jurassic",
      "font_class": "jurassic_add-user",
      "unicode": "e6ed",
      "unicode_decimal": 59117
    },
    {
      "icon_id": "10792667",
      "name": "编辑角色信息_编辑录入操作_jurassic",
      "font_class": "jurassic_edit-user",
      "unicode": "e6f2",
      "unicode_decimal": 59122
    },
    {
      "icon_id": "10807900",
      "name": "选择模块-绘制热区",
      "font_class": "xuanzemokuai-huizhirequ",
      "unicode": "e60f",
      "unicode_decimal": 58895
    },
    {
      "icon_id": "11121397",
      "name": "角色管理",
      "font_class": "jiaoseguanli",
      "unicode": "e62d",
      "unicode_decimal": 58925
    },
    {
      "icon_id": "11121446",
      "name": "数据角色权限管理",
      "font_class": "shujujiaosequanxianguanli",
      "unicode": "e637",
      "unicode_decimal": 58935
    },
    {
      "icon_id": "12080793",
      "name": "权限",
      "font_class": "quanxian1",
      "unicode": "e60c",
      "unicode_decimal": 58892
    },
    {
      "icon_id": "12517042",
      "name": "排序",
      "font_class": "order1",
      "unicode": "e605",
      "unicode_decimal": 58885
    },
    {
      "icon_id": "12630287",
      "name": "店铺",
      "font_class": "dianpu",
      "unicode": "e763",
      "unicode_decimal": 59235
    },
    {
      "icon_id": "13157516",
      "name": "排序",
      "font_class": "paixu",
      "unicode": "e6bb",
      "unicode_decimal": 59067
    },
    {
      "icon_id": "13385780",
      "name": "模块-产品库",
      "font_class": "mokuai-chanpinku",
      "unicode": "e6c5",
      "unicode_decimal": 59077
    },
    {
      "icon_id": "16205692",
      "name": "日志",
      "font_class": "rizhi",
      "unicode": "e68e",
      "unicode_decimal": 59022
    },
    {
      "icon_id": "17960640",
      "name": "学校",
      "font_class": "xuexiao",
      "unicode": "e85f",
      "unicode_decimal": 59487
    },
    {
      "icon_id": "18533068",
      "name": "角色",
      "font_class": "jiaose",
      "unicode": "e606",
      "unicode_decimal": 58886
    },
    {
      "icon_id": "2380627",
      "name": "返回2",
      "font_class": "fanhui",
      "unicode": "e609",
      "unicode_decimal": 58889
    },
    {
      "icon_id": "3248648",
      "name": "返回",
      "font_class": "fanhui2",
      "unicode": "e608",
      "unicode_decimal": 58888
    },
    {
      "icon_id": "8355722",
      "name": "刷新",
      "font_class": "shuaxin",
      "unicode": "e662",
      "unicode_decimal": 58978
    },
    {
      "icon_id": "326917",
      "name": "出库",
      "font_class": "iconfontguanlibumen2",
      "unicode": "e60a",
      "unicode_decimal": 58890
    },
    {
      "icon_id": "554168",
      "name": "搜索文件夹",
      "font_class": "iconset0199",
      "unicode": "e663",
      "unicode_decimal": 58979
    },
    {
      "icon_id": "607162",
      "name": "商品出库列表-增加",
      "font_class": "inv-add",
      "unicode": "e60b",
      "unicode_decimal": 58891
    },
    {
      "icon_id": "754744",
      "name": "测绘发布-文件夹01",
      "font_class": "cehuifabuwenjianjia01",
      "unicode": "e63c",
      "unicode_decimal": 58940
    },
    {
      "icon_id": "754749",
      "name": "系统运维-打开文件夹",
      "font_class": "xitongyunweidakaiwenjianjia",
      "unicode": "e644",
      "unicode_decimal": 58948
    },
    {
      "icon_id": "792392",
      "name": "folder6-文件夹",
      "font_class": "folder6wenjianjia",
      "unicode": "e6cf",
      "unicode_decimal": 59087
    },
    {
      "icon_id": "792394",
      "name": "folder4-文件夹",
      "font_class": "folder4wenjianjia",
      "unicode": "e6d1",
      "unicode_decimal": 59089
    },
    {
      "icon_id": "792396",
      "name": "folder2-文件夹",
      "font_class": "folder2wenjianjia",
      "unicode": "e6d3",
      "unicode_decimal": 59091
    },
    {
      "icon_id": "934870",
      "name": "文件夹",
      "font_class": "7",
      "unicode": "e611",
      "unicode_decimal": 58897
    },
    {
      "icon_id": "2383212",
      "name": "统计",
      "font_class": "tongji",
      "unicode": "e628",
      "unicode_decimal": 58920
    },
    {
      "icon_id": "3315394",
      "name": "统计",
      "font_class": "tongji2",
      "unicode": "e63e",
      "unicode_decimal": 58942
    },
    {
      "icon_id": "5334135",
      "name": "城市",
      "font_class": "chengshi",
      "unicode": "e613",
      "unicode_decimal": 58899
    },
    {
      "icon_id": "5351337",
      "name": "扫码出库",
      "font_class": "saomachuku",
      "unicode": "e656",
      "unicode_decimal": 58966
    },
    {
      "icon_id": "6298975",
      "name": "城市布控",
      "font_class": "icon-",
      "unicode": "e665",
      "unicode_decimal": 58981
    },
    {
      "icon_id": "9199728",
      "name": "统计",
      "font_class": "tongji3",
      "unicode": "e721",
      "unicode_decimal": 59169
    },
    {
      "icon_id": "9448106",
      "name": "报表",
      "font_class": "baobiao",
      "unicode": "e6a1",
      "unicode_decimal": 59041
    },
    {
      "icon_id": "9955817",
      "name": "报表",
      "font_class": "baobiao1",
      "unicode": "e61b",
      "unicode_decimal": 58907
    },
    {
      "icon_id": "9967356",
      "name": "统计",
      "font_class": "tongji4",
      "unicode": "e6e0",
      "unicode_decimal": 59104
    },
    {
      "icon_id": "10094540",
      "name": "统计公告",
      "font_class": "tongjigonggao",
      "unicode": "e712",
      "unicode_decimal": 59154
    },
    {
      "icon_id": "10404760",
      "name": "统计分析",
      "font_class": "tongji5",
      "unicode": "e61c",
      "unicode_decimal": 58908
    },
    {
      "icon_id": "11338378",
      "name": "入库",
      "font_class": "ruku",
      "unicode": "e61e",
      "unicode_decimal": 58910
    },
    {
      "icon_id": "11610178",
      "name": "统计功能",
      "font_class": "tongjigongneng",
      "unicode": "e620",
      "unicode_decimal": 58912
    },
    {
      "icon_id": "11711114",
      "name": "文件夹",
      "font_class": "wenjianjia",
      "unicode": "e630",
      "unicode_decimal": 58928
    },
    {
      "icon_id": "11871724",
      "name": "进出库记录",
      "font_class": "jinchukujilu",
      "unicode": "e629",
      "unicode_decimal": 58921
    },
    {
      "icon_id": "11912390",
      "name": "出库审批",
      "font_class": "tubiao_chukushenpi",
      "unicode": "e62b",
      "unicode_decimal": 58923
    },
    {
      "icon_id": "12859845",
      "name": "统计",
      "font_class": "tongji7",
      "unicode": "e62e",
      "unicode_decimal": 58926
    },
    {
      "icon_id": "12905588",
      "name": "office",
      "font_class": "office",
      "unicode": "e638",
      "unicode_decimal": 58936
    },
    {
      "icon_id": "12981334",
      "name": "文件夹",
      "font_class": "zhuanlan",
      "unicode": "e62f",
      "unicode_decimal": 58927
    },
    {
      "icon_id": "13254843",
      "name": "进销存",
      "font_class": "jinxiaocun",
      "unicode": "e6d0",
      "unicode_decimal": 59088
    },
    {
      "icon_id": "14435421",
      "name": "统计",
      "font_class": "tongji8",
      "unicode": "e657",
      "unicode_decimal": 58967
    },
    {
      "icon_id": "14742468",
      "name": "出库单",
      "font_class": "chukudan",
      "unicode": "e83e",
      "unicode_decimal": 59454
    },
    {
      "icon_id": "15055949",
      "name": "文件夹",
      "font_class": "wenjianjia1",
      "unicode": "e647",
      "unicode_decimal": 58951
    },
    {
      "icon_id": "15394209",
      "name": "文件，文件夹，目录",
      "font_class": "Folder-directory",
      "unicode": "e632",
      "unicode_decimal": 58930
    },
    {
      "icon_id": "15713951",
      "name": "统计",
      "font_class": "tongji9",
      "unicode": "e785",
      "unicode_decimal": 59269
    },
    {
      "icon_id": "17457890",
      "name": "新增出库退货单",
      "font_class": "xinzengchukutuihuodan",
      "unicode": "e719",
      "unicode_decimal": 59161
    },
    {
      "icon_id": "17486525",
      "name": "统计",
      "font_class": "tongji10",
      "unicode": "e634",
      "unicode_decimal": 58932
    },
    {
      "icon_id": "17667171",
      "name": "出库纪录",
      "font_class": "chukujilu",
      "unicode": "e672",
      "unicode_decimal": 58994
    },
    {
      "icon_id": "18594841",
      "name": "需出库",
      "font_class": "xuchuku",
      "unicode": "e635",
      "unicode_decimal": 58933
    },
    {
      "icon_id": "19024042",
      "name": "04出口-库存-出库单管理",
      "font_class": "04chukou-kucun-chukudanguanli",
      "unicode": "e670",
      "unicode_decimal": 58992
    },
    {
      "icon_id": "2491930",
      "name": "出库",
      "font_class": "chuku1",
      "unicode": "e6d4",
      "unicode_decimal": 59092
    },
    {
      "icon_id": "6343735",
      "name": "库存流水",
      "font_class": "kucunliushui",
      "unicode": "e652",
      "unicode_decimal": 58962
    },
    {
      "icon_id": "7459454",
      "name": "其他出库",
      "font_class": "tubiaochicundaochuSVGshangchuandaoalibaba-",
      "unicode": "e636",
      "unicode_decimal": 58934
    },
    {
      "icon_id": "10157588",
      "name": "出库",
      "font_class": "chuku2",
      "unicode": "e68f",
      "unicode_decimal": 59023
    },
    {
      "icon_id": "11361330",
      "name": "历史出库情况",
      "font_class": "lishichukuqingkuang",
      "unicode": "e66e",
      "unicode_decimal": 58990
    },
    {
      "icon_id": "11433256",
      "name": "出库预约单",
      "font_class": "chukuyuyuedan",
      "unicode": "e639",
      "unicode_decimal": 58937
    },
    {
      "icon_id": "12987487",
      "name": "调拨出库单_1",
      "font_class": "tiaobochukudan_",
      "unicode": "e65e",
      "unicode_decimal": 58974
    },
    {
      "icon_id": "11235820",
      "name": "seach",
      "font_class": "seach",
      "unicode": "e74b",
      "unicode_decimal": 59211
    },
    {
      "icon_id": "17291984",
      "name": "表格-审核",
      "font_class": "shenhe",
      "unicode": "e648",
      "unicode_decimal": 58952
    },
    {
      "icon_id": "17852827",
      "name": "图片@2x",
      "font_class": "tupian2x",
      "unicode": "e63b",
      "unicode_decimal": 58939
    },
    {
      "icon_id": "17882484",
      "name": "导出",
      "font_class": "daochu",
      "unicode": "e666",
      "unicode_decimal": 58982
    },
    {
      "icon_id": "17882700",
      "name": "导入",
      "font_class": "daoru",
      "unicode": "e667",
      "unicode_decimal": 58983
    },
    {
      "icon_id": "18369076",
      "name": "62",
      "font_class": "62",
      "unicode": "e6e7",
      "unicode_decimal": 59111
    },
    {
      "icon_id": "18533069",
      "name": "全选建群",
      "font_class": "quanxuanjianqun",
      "unicode": "e64b",
      "unicode_decimal": 58955
    },
    {
      "icon_id": "18533072",
      "name": "权限管理",
      "font_class": "quanxianguanli1",
      "unicode": "e64c",
      "unicode_decimal": 58956
    },
    {
      "icon_id": "18681353",
      "name": "1-2-1-缓存",
      "font_class": "1-2-1-huancun",
      "unicode": "e64e",
      "unicode_decimal": 58958
    },
    {
      "icon_id": "18758732",
      "name": "仪表2",
      "font_class": "yibiao2",
      "unicode": "e64f",
      "unicode_decimal": 58959
    },
    {
      "icon_id": "18853281",
      "name": "信息发布",
      "font_class": "xinxifabu",
      "unicode": "e681",
      "unicode_decimal": 59009
    },
    {
      "icon_id": "19105727",
      "name": "编码",
      "font_class": "bianma",
      "unicode": "e772",
      "unicode_decimal": 59250
    },
    {
      "icon_id": "19105814",
      "name": "扫码-big",
      "font_class": "saoma-big",
      "unicode": "e774",
      "unicode_decimal": 59252
    },
    {
      "icon_id": "19105815",
      "name": "扫码",
      "font_class": "saoma1",
      "unicode": "e775",
      "unicode_decimal": 59253
    },
    {
      "icon_id": "19233403",
      "name": "评论",
      "font_class": "pinglun",
      "unicode": "e651",
      "unicode_decimal": 58961
    },
    {
      "icon_id": "19233405",
      "name": "收藏",
      "font_class": "shoucang1",
      "unicode": "e658",
      "unicode_decimal": 58968
    },
    {
      "icon_id": "19233407",
      "name": "问答",
      "font_class": "wenda",
      "unicode": "e65b",
      "unicode_decimal": 58971
    },
    {
      "icon_id": "16137336",
      "name": "报表",
      "font_class": "baobiao2",
      "unicode": "e7c6",
      "unicode_decimal": 59334
    },
    {
      "icon_id": "16158845",
      "name": "会员权益",
      "font_class": "huiyuanquanyi",
      "unicode": "e7e6",
      "unicode_decimal": 59366
    },
    {
      "icon_id": "4511698",
      "name": "出库",
      "font_class": "chuku3",
      "unicode": "e69e",
      "unicode_decimal": 59038
    },
    {
      "icon_id": "4511699",
      "name": "入库",
      "font_class": "ruku1",
      "unicode": "e69f",
      "unicode_decimal": 59039
    },
    {
      "icon_id": "16147991",
      "name": "出库管理",
      "font_class": "chukuguanli1",
      "unicode": "e65c",
      "unicode_decimal": 58972
    },
    {
      "icon_id": "18450531",
      "name": "待出库",
      "font_class": "daichuku1",
      "unicode": "e65f",
      "unicode_decimal": 58975
    },
    {
      "icon_id": "495876",
      "name": "优惠券",
      "font_class": "youhuiquan",
      "unicode": "e660",
      "unicode_decimal": 58976
    },
    {
      "icon_id": "1058192",
      "name": "优惠券",
      "font_class": "youhuiquan1",
      "unicode": "e668",
      "unicode_decimal": 58984
    },
    {
      "icon_id": "17542140",
      "name": "我的-抢购订单",
      "font_class": "wode-qianggoudingdan",
      "unicode": "e66c",
      "unicode_decimal": 58988
    },
    {
      "icon_id": "332560",
      "name": "微信登录",
      "font_class": "weixindenglu",
      "unicode": "e7c2",
      "unicode_decimal": 59330
    },
    {
      "icon_id": "704501",
      "name": "商品申购",
      "font_class": "shangpinshengou",
      "unicode": "e691",
      "unicode_decimal": 59025
    },
    {
      "icon_id": "947113",
      "name": "我的",
      "font_class": "wode",
      "unicode": "e66d",
      "unicode_decimal": 58989
    },
    {
      "icon_id": "1435228",
      "name": "分类",
      "font_class": "fenlei",
      "unicode": "e66f",
      "unicode_decimal": 58991
    },
    {
      "icon_id": "1788966",
      "name": "分享",
      "font_class": "fenxiang1",
      "unicode": "e6a4",
      "unicode_decimal": 59044
    },
    {
      "icon_id": "7473697",
      "name": "商品管理",
      "font_class": "shangpinguanli1",
      "unicode": "e673",
      "unicode_decimal": 58995
    },
    {
      "icon_id": "12975013",
      "name": "商品",
      "font_class": "shangpin",
      "unicode": "e677",
      "unicode_decimal": 58999
    },
    {
      "icon_id": "17558825",
      "name": "订单",
      "font_class": "dingdan",
      "unicode": "e67b",
      "unicode_decimal": 59003
    },
    {
      "icon_id": "18522248",
      "name": "首页",
      "font_class": "shouye",
      "unicode": "e67c",
      "unicode_decimal": 59004
    },
    {
      "icon_id": "2594648",
      "name": "礼盒",
      "font_class": "lihe",
      "unicode": "e67e",
      "unicode_decimal": 59006
    },
    {
      "icon_id": "7940245",
      "name": "打印机",
      "font_class": "dayinji",
      "unicode": "e67f",
      "unicode_decimal": 59007
    },
    {
      "icon_id": "10392627",
      "name": "通知",
      "font_class": "tongzhi",
      "unicode": "e680",
      "unicode_decimal": 59008
    },
    {
      "icon_id": "12323752",
      "name": "关闭",
      "font_class": "guanbi",
      "unicode": "e682",
      "unicode_decimal": 59010
    },
    {
      "icon_id": "15109287",
      "name": "分享",
      "font_class": "fenxiang2",
      "unicode": "e6ae",
      "unicode_decimal": 59054
    },
    {
      "icon_id": "2017934",
      "name": "排行榜",
      "font_class": "paihangbang",
      "unicode": "e683",
      "unicode_decimal": 59011
    },
    {
      "icon_id": "20630721",
      "name": "我的-面性",
      "font_class": "geren-mianxing",
      "unicode": "e684",
      "unicode_decimal": 59012
    },
    {
      "icon_id": "20630725",
      "name": "我的-线性",
      "font_class": "geren-xianxing",
      "unicode": "e685",
      "unicode_decimal": 59013
    },
    {
      "icon_id": "2170591",
      "name": "订单-1",
      "font_class": "dingdan-",
      "unicode": "e687",
      "unicode_decimal": 59015
    },
    {
      "icon_id": "792997",
      "name": "订单",
      "font_class": "orders",
      "unicode": "e690",
      "unicode_decimal": 59024
    },
    {
      "icon_id": "197930",
      "name": "进货选中",
      "font_class": "jinhuoxuanzhong",
      "unicode": "e689",
      "unicode_decimal": 59017
    },
    {
      "icon_id": "6941545",
      "name": "进货宝",
      "font_class": "jinhuobao",
      "unicode": "e6a0",
      "unicode_decimal": 59040
    },
    {
      "icon_id": "13878740",
      "name": "shouye",
      "font_class": "shouye1",
      "unicode": "e68a",
      "unicode_decimal": 59018
    },
    {
      "icon_id": "20606245",
      "name": "shouye",
      "font_class": "shouye2",
      "unicode": "e692",
      "unicode_decimal": 59026
    },
    {
      "icon_id": "4170365",
      "name": "支付宝支付",
      "font_class": "zhifubaozhifu",
      "unicode": "e686",
      "unicode_decimal": 59014
    },
    {
      "icon_id": "5238520",
      "name": "银行卡",
      "font_class": "shuaqiaqiapianyinhangqia",
      "unicode": "e693",
      "unicode_decimal": 59027
    },
    {
      "icon_id": "12247360",
      "name": "微信 支付",
      "font_class": "weixinzhifu1",
      "unicode": "e694",
      "unicode_decimal": 59028
    },
    {
      "icon_id": "14065644",
      "name": "微信 支付",
      "font_class": "wxpay1",
      "unicode": "e695",
      "unicode_decimal": 59029
    },
    {
      "icon_id": "18076033",
      "name": "支付宝支付",
      "font_class": "zhifubaozhifu1",
      "unicode": "e696",
      "unicode_decimal": 59030
    },
    {
      "icon_id": "6941954",
      "name": "未绑定",
      "font_class": "weibangding",
      "unicode": "e697",
      "unicode_decimal": 59031
    },
    {
      "icon_id": "6941955",
      "name": "已绑定",
      "font_class": "yibangding",
      "unicode": "e698",
      "unicode_decimal": 59032
    },
    {
      "icon_id": "1331102",
      "name": "wheel",
      "font_class": "wheel",
      "unicode": "e61d",
      "unicode_decimal": 58909
    },
    {
      "icon_id": "1358905",
      "name": "rank",
      "font_class": "rank",
      "unicode": "e63a",
      "unicode_decimal": 58938
    },
    {
      "icon_id": "5269225",
      "name": "财务",
      "font_class": "caiwu",
      "unicode": "e62c",
      "unicode_decimal": 58924
    },
    {
      "icon_id": "5663607",
      "name": "绿色家",
      "font_class": "lvsejia",
      "unicode": "e63f",
      "unicode_decimal": 58943
    },
    {
      "icon_id": "10549653",
      "name": "GIS应用",
      "font_class": "GISyingyong",
      "unicode": "e678",
      "unicode_decimal": 59000
    },
    {
      "icon_id": "19954239",
      "name": "更多拼团",
      "font_class": "gengduopintuan",
      "unicode": "e649",
      "unicode_decimal": 58953
    },
    {
      "icon_id": "21169744",
      "name": "拼团",
      "font_class": "pintuan",
      "unicode": "e64d",
      "unicode_decimal": 58957
    },
    {
      "icon_id": "27243072",
      "name": "应用",
      "font_class": "xialingyingicon-01",
      "unicode": "e61f",
      "unicode_decimal": 58911
    },
    {
      "icon_id": "10983",
      "name": "主题服务分类",
      "font_class": "zhutifuwufenlei",
      "unicode": "e603",
      "unicode_decimal": 58883
    },
    {
      "icon_id": "49193",
      "name": "退出",
      "font_class": "tuichu",
      "unicode": "e607",
      "unicode_decimal": 58887
    },
    {
      "icon_id": "90879",
      "name": "营销活动",
      "font_class": "yingxiao",
      "unicode": "e659",
      "unicode_decimal": 58969
    },
    {
      "icon_id": "92511",
      "name": "下载",
      "font_class": "xiazai",
      "unicode": "e7a3",
      "unicode_decimal": 59299
    },
    {
      "icon_id": "104263",
      "name": "分享",
      "font_class": "fenxiang",
      "unicode": "e615",
      "unicode_decimal": 58901
    },
    {
      "icon_id": "106923",
      "name": "收藏",
      "font_class": "shoucang",
      "unicode": "e618",
      "unicode_decimal": 58904
    },
    {
      "icon_id": "127291",
      "name": "抽奖",
      "font_class": "choujiang",
      "unicode": "e62a",
      "unicode_decimal": 58922
    },
    {
      "icon_id": "136419",
      "name": "公文包",
      "font_class": "iconfontcolor63",
      "unicode": "e6bc",
      "unicode_decimal": 59068
    },
    {
      "icon_id": "203314",
      "name": "消息",
      "font_class": "xiaoxi",
      "unicode": "e623",
      "unicode_decimal": 58915
    },
    {
      "icon_id": "213654",
      "name": "地图",
      "font_class": "ditu",
      "unicode": "e614",
      "unicode_decimal": 58900
    },
    {
      "icon_id": "278897",
      "name": "产品库",
      "font_class": "chanpinku",
      "unicode": "e621",
      "unicode_decimal": 58913
    },
    {
      "icon_id": "382889",
      "name": "测评",
      "font_class": "ceping",
      "unicode": "e631",
      "unicode_decimal": 58929
    },
    {
      "icon_id": "383281",
      "name": "表情-笑脸",
      "font_class": "biaoqingxiaolian",
      "unicode": "e625",
      "unicode_decimal": 58917
    },
    {
      "icon_id": "395438",
      "name": "运维管理平台",
      "font_class": "yunweiguanlipingtai",
      "unicode": "e72b",
      "unicode_decimal": 59179
    },
    {
      "icon_id": "457302",
      "name": "样式配置",
      "font_class": "xtgl6",
      "unicode": "e6eb",
      "unicode_decimal": 59115
    },
    {
      "icon_id": "557742",
      "name": "特殊订购",
      "font_class": "teshudinggou",
      "unicode": "e64a",
      "unicode_decimal": 58954
    },
    {
      "icon_id": "723341",
      "name": "红包",
      "font_class": "ai-hongbao",
      "unicode": "e616",
      "unicode_decimal": 58902
    },
    {
      "icon_id": "742611",
      "name": "商品管理",
      "font_class": "shangpinguanli",
      "unicode": "e63d",
      "unicode_decimal": 58941
    },
    {
      "icon_id": "861356",
      "name": "营销模块",
      "font_class": "yingxiaomokuai",
      "unicode": "e622",
      "unicode_decimal": 58914
    },
    {
      "icon_id": "876875",
      "name": "文件",
      "font_class": "wenjian",
      "unicode": "e664",
      "unicode_decimal": 58980
    },
    {
      "icon_id": "943885",
      "name": "社交网络",
      "font_class": "shejiaowangluo",
      "unicode": "e69b",
      "unicode_decimal": 59035
    },
    {
      "icon_id": "1017662",
      "name": "红包",
      "font_class": "hongbao2",
      "unicode": "e688",
      "unicode_decimal": 59016
    },
    {
      "icon_id": "1063815",
      "name": "云台-点击-01",
      "font_class": "yuntaidianji01",
      "unicode": "e640",
      "unicode_decimal": 58944
    },
    {
      "icon_id": "1105066",
      "name": "资金台账",
      "font_class": "zijintaizhang",
      "unicode": "e641",
      "unicode_decimal": 58945
    },
    {
      "icon_id": "1111044",
      "name": "Drgs平台软件系统37",
      "font_class": "drgspingtairuanjianxitong37",
      "unicode": "e650",
      "unicode_decimal": 58960
    },
    {
      "icon_id": "1151328",
      "name": "系统配额",
      "font_class": "xitongpeie",
      "unicode": "e65a",
      "unicode_decimal": 58970
    },
    {
      "icon_id": "1162162",
      "name": "分销平台",
      "font_class": "fenxiaopingtai",
      "unicode": "e654",
      "unicode_decimal": 58964
    },
    {
      "icon_id": "1208849",
      "name": "活动",
      "font_class": "huodong",
      "unicode": "e671",
      "unicode_decimal": 58993
    },
    {
      "icon_id": "1234477",
      "name": "平台",
      "font_class": "pingtai",
      "unicode": "e661",
      "unicode_decimal": 58977
    },
    {
      "icon_id": "1021297",
      "name": "支付宝",
      "font_class": "big-Pay",
      "unicode": "e6ec",
      "unicode_decimal": 59116
    },
    {
      "icon_id": "4320333",
      "name": "打印",
      "font_class": "dayin",
      "unicode": "e68d",
      "unicode_decimal": 59021
    },
    {
      "icon_id": "6848505",
      "name": "日期",
      "font_class": "riqi",
      "unicode": "e68b",
      "unicode_decimal": 59019
    },
    {
      "icon_id": "777250",
      "name": "余额",
      "font_class": "yue1",
      "unicode": "e624",
      "unicode_decimal": 58916
    },
    {
      "icon_id": "3402673",
      "name": "积分",
      "font_class": "jifen5",
      "unicode": "e60d",
      "unicode_decimal": 58893
    },
    {
      "icon_id": "8629854",
      "name": "地址",
      "font_class": "dizhi",
      "unicode": "e6ba",
      "unicode_decimal": 59066
    },
    {
      "icon_id": "8629861",
      "name": "余额",
      "font_class": "yue",
      "unicode": "e6c1",
      "unicode_decimal": 59073
    },
    {
      "icon_id": "8629867",
      "name": "提现",
      "font_class": "tixian",
      "unicode": "e6c7",
      "unicode_decimal": 59079
    },
    {
      "icon_id": "8631124",
      "name": "售后",
      "font_class": "shouhou",
      "unicode": "e6d6",
      "unicode_decimal": 59094
    },
    {
      "icon_id": "8631127",
      "name": "待评价",
      "font_class": "daipingjia",
      "unicode": "e6d9",
      "unicode_decimal": 59097
    },
    {
      "icon_id": "1221709",
      "name": "限时抢购",
      "font_class": "xianshiqianggou",
      "unicode": "e633",
      "unicode_decimal": 58931
    }
  ]
}
